msiimport/__init__.py
msiimport-0.1.0.dist-info/LICENCE
msiimport-0.1.0.dist-info/METADATA
msiimport-0.1.0.dist-info/WHEEL
msiimport-0.1.0.dist-info/top_level.txt
msiimport-0.1.0.dist-info/RECORD
