Metadata-Version: 2.1
Name: msiimport
Version: 0.1.0
Summary: Access analyze75 formatted mass spec images
Home-page: https://github.com/STTARR/msiimport
Author: Jade Bilkey
Author-email: python@thefumon.com
License: UNKNOWN
Platform: UNKNOWN
Classifier: Development Status :: 3 - Alpha
Classifier: Intended Audience :: Science/Research
Classifier: License :: OSI Approved :: MIT License
Classifier: Operating System :: OS Independent
Classifier: Programming Language :: Python
Classifier: Topic :: Scientific/Engineering :: Medical Science Apps.
Requires-Dist: numpy
Requires-Dist: nibabel
